.bumpversion.cfg
.cookiecutterrc
.coveragerc
.editorconfig
.gitignore
.pre-commit-config.yaml
.readthedocs.yml
AUTHORS.rst
CHANGELOG.rst
CONTRIBUTING.rst
LICENSE
README.rst
pyproject.toml
pytest.ini
requirements.txt
setup.cfg
setup.py
tox.ini
.github/workflows/github-actions.yml
ci/bootstrap.py
ci/requirements.txt
ci/templates/tox.ini
ci/templates/.github/workflows/github-actions.yml
docs/authors.rst
docs/changelog.rst
docs/conf.py
docs/contributing.rst
docs/index.rst
docs/installation.rst
docs/readme.rst
docs/requirements.txt
docs/spelling_wordlist.txt
docs/usage.rst
docs/reference/index.rst
docs/reference/lazy_qa.rst
src/lazy_qa/__init__.py
src/lazy_qa/__main__.py
src/lazy_qa/_lazy_qa.c
src/lazy_qa/_version.py
src/lazy_qa/cli.py
src/lazy_qa/csv_builder.py
src/lazy_qa/database_mysql.py
src/lazy_qa/database_postgresql.py
src/lazy_qa/json_builder.py
src/lazy_qa/list_manipulation.py
src/lazy_qa/request_builder.py
src/lazy_qa/string_manipulation.py
src/lazy_qa/yaml_manipulation.py
src/lazy_qa.egg-info/PKG-INFO
src/lazy_qa.egg-info/SOURCES.txt
src/lazy_qa.egg-info/dependency_links.txt
src/lazy_qa.egg-info/entry_points.txt
src/lazy_qa.egg-info/not-zip-safe
src/lazy_qa.egg-info/top_level.txt
tests/test_lazy_qa.py