Metadata-Version: 1.2
Name: lazy-qa
Version: 0.0.1.dev8
Summary:   
Home-page: https://github.com/angeleyesffx/lazy_qa
Author: Priscilla Rodrigues Martins
Author-email: angeleyes.ffx@hotmail.com
License: MIT
Project-URL: Documentation, https://lazy_qa.readthedocs.io/
Project-URL: Changelog, https://lazy_qa.readthedocs.io/en/latest/changelog.html
Project-URL: Issue Tracker, https://github.com/angeleyesffx/lazy_qa/issues
Platform: UNKNOWN
Classifier: Development Status :: 5 - Production/Stable
Classifier: Intended Audience :: Developers
Classifier: License :: OSI Approved :: MIT License
Classifier: Operating System :: Unix
Classifier: Operating System :: POSIX
Classifier: Operating System :: Microsoft :: Windows
Classifier: Programming Language :: Python
Classifier: Programming Language :: Python :: 3
Classifier: Programming Language :: Python :: 3 :: Only
Classifier: Programming Language :: Python :: 3.6
Classifier: Programming Language :: Python :: 3.7
Classifier: Programming Language :: Python :: 3.8
Classifier: Programming Language :: Python :: 3.9
Classifier: Programming Language :: Python :: 3.10
Classifier: Programming Language :: Python :: Implementation :: CPython
Classifier: Programming Language :: Python :: Implementation :: PyPy
Classifier: Topic :: Utilities
Requires-Python: >=3.6
